docker_registry_driver_alioss-0.1.1-py2.7-nspkg.pth
docker_registry_driver_alioss-0.1.1.dist-info/namespace_packages.txt
docker_registry_driver_alioss-0.1.1.dist-info/metadata.json
docker_registry_driver_alioss-0.1.1.dist-info/DESCRIPTION.rst
docker_registry_driver_alioss-0.1.1.dist-info/RECORD
docker_registry_driver_alioss-0.1.1.dist-info/top_level.txt
docker_registry_driver_alioss-0.1.1.dist-info/WHEEL
docker_registry_driver_alioss-0.1.1.dist-info/METADATA
docker_registry/drivers/alioss.py
