Metadata-Version: 2.0
Name: docker-registry-driver-alioss
Version: 0.1.1
Summary: Docker registry ali oss driver
Home-page: https://github.com/chris-jin/docker-registry-driver-alioss
Author: Chris Jin
Author-email: chrisjin@outlook.com
License: Apache License
Requires-Dist: docker-registry-core (>=2,<3)
Requires-Dist: oss (==0.1.3)
